sysl/__init__.py
sysl/__version__.py
sysl/core/__init__.py
sysl/core/__main__.py
sysl/core/syslalgo.py
sysl/core/sysldata.py
sysl/core/syslints.py
sysl/core/syslloader.py
sysl/core/syslparse.py
sysl/core/syslseqs.py
sysl/core/syslx.py
sysl/exporters/__init__.py
sysl/exporters/api/__init__.py
sysl/exporters/api/spring_rest.py
sysl/exporters/java/__init__.py
sysl/exporters/java/facade.py
sysl/exporters/java/model.py
sysl/exporters/js/__init__.py
sysl/exporters/js/js_model.py
sysl/exporters/json_out/__init__.py
sysl/exporters/json_out/serializer.py
sysl/exporters/swagger/__init__.py
sysl/exporters/swagger/swagger.py
sysl/exporters/xml/__init__.py
sysl/exporters/xml/serializer.py
sysl/exporters/xml/xsd.py
sysl/importers/__init__.py
sysl/importers/import_swagger.py
sysl/importers/import_xsd.py
sysl/proto/__init__.py
sysl/proto/sysl_pb2.py
sysl/reljam/__init__.py
sysl/reljam/__main__.py
sysl/reljam/reljam.py
sysl/util/__init__.py
sysl/util/algo.py
sysl/util/argparse.py
sysl/util/cache.py
sysl/util/confluence.py
sysl/util/datamodel.py
sysl/util/debug.py
sysl/util/diagutil.py
sysl/util/file.py
sysl/util/java.py
sysl/util/rex.py
sysl/util/scopes.py
sysl/util/simple_parser.py
sysl/util/writer.py
sysl-0.3.0.dist-info/AUTHORS.yml
sysl-0.3.0.dist-info/LICENSE
sysl-0.3.0.dist-info/METADATA
sysl-0.3.0.dist-info/WHEEL
sysl-0.3.0.dist-info/entry_points.txt
sysl-0.3.0.dist-info/top_level.txt
sysl-0.3.0.dist-info/RECORD
