Metadata-Version: 2.1
Name: sysl
Version: 0.3.0
Summary: System specification language with compiler and code generator
Home-page: https://github.com/anz-bank/sysl
Author: ANZ
Author-email: marcelo.cantos@anz.com
License: Apache 2.0
Platform: UNKNOWN
Classifier: License :: OSI Approved :: Apache Software License
Classifier: Programming Language :: Python
Classifier: Programming Language :: Python :: 2.7
Requires-Dist: httplib2
Requires-Dist: urllib3 (==1.24.2)
Requires-Dist: openpyxl
Requires-Dist: plantuml
Requires-Dist: protobuf
Requires-Dist: pylint
Requires-Dist: PyYAML
Requires-Dist: requests
Requires-Dist: six
Provides-Extra: dev
Requires-Dist: pytest ; extra == 'dev'
Requires-Dist: flake8 ; extra == 'dev'
